jsonp2/__init__.py
jsonp2-1.0.1.dist-info/LICENSE
jsonp2-1.0.1.dist-info/METADATA
jsonp2-1.0.1.dist-info/WHEEL
jsonp2-1.0.1.dist-info/top_level.txt
jsonp2-1.0.1.dist-info/RECORD
