Metadata-Version: 2.1
Name: jsonp2
Version: 1.0.1
Summary: jsonp to json
Home-page: https://github.com/jiang1243754883/jsonp2/tree/master
Author: spider_jiang
Author-email: author@example.com
Classifier: Programming Language :: Python :: 3
Classifier: License :: OSI Approved :: MIT License
Classifier: Operating System :: OS Independent
License-File: LICENSE
